pyhtmlinfo/__init__.py
pyhtmlinfo/src.py
pyhtmlinfo-0.2.0.dist-info/LICENSE
pyhtmlinfo-0.2.0.dist-info/METADATA
pyhtmlinfo-0.2.0.dist-info/WHEEL
pyhtmlinfo-0.2.0.dist-info/top_level.txt
pyhtmlinfo-0.2.0.dist-info/RECORD
